[{"content":"社长和lulu在联动","time":1671624749000,"price":30,"user":{"uid":227762853,"name":"浮生若梦的亦客"},"medal":{"level":7,"name":"蓝耳朵","boat":0}},{"content":"烧烤+啤酒+直播，快乐的夜晚又开始了","time":1671624848000,"price":50,"user":{"uid":206226312,"name":"切片观赏仙人"},"medal":{"level":11,"name":"魔咪民","boat":0}},{"content":"白菜我的好朋友依诺今天过生日，可以祝她生日快乐吗","time":1671624880000,"price":50,"user":{"uid":629024890,"name":"晚风-抚柳"},"medal":{"level":21,"name":"帕清姬","boat":3}},{"content":"白菜~momo社长布置的中文作业记得做哦~12月快结束了~马上就一月份啦~","time":1671625044000,"price":30,"user":{"uid":7387975,"name":"l喵喵兔兔"},"medal":{"level":25,"name":"帕清姬","boat":3}},{"content":"白菜ならきっと出来る！楽しんでいきましょう！","time":1671625253000,"price":30,"user":{"uid":487364787,"name":"Purin_琦玉老哥"},"medal":{"level":29,"name":"帕清姬","boat":3}},{"content":"你说我是今天上舰好还是明天上舰呢？","time":1671625253000,"price":30,"user":{"uid":2024175089,"name":"玥-殇璃"},"medal":{"level":12,"name":"帕清姬","boat":0}},{"content":"白菜以后不能那么屑了，不然被欧拉欧拉的就是fufu了（","time":1671625484000,"price":30,"user":{"uid":5832086,"name":"yuncai0077"},"medal":{"level":26,"name":"帕清姬","boat":0}},{"content":"社长和lulu在联动，要不要去看看？","time":1671625524000,"price":30,"user":{"uid":227762853,"name":"浮生若梦的亦客"},"medal":{"level":7,"name":"蓝耳朵","boat":0}},{"content":"明天的抽奖我一定不会失手","time":1671625556000,"price":30,"user":{"uid":246954,"name":"edeN滸"},"medal":{"level":29,"name":"帕清姬","boat":2}},{"content":"比起fufu，大家可能更想要挂起来的沙包啊","time":1671625780000,"price":30,"user":{"uid":39358662,"name":"黑山羊不吃草"},"medal":{"level":22,"name":"魔咪民","boat":0}},{"content":"白菜は本番に強いタイプだからステージに上がればきっとうまくいける！頑張ってね！","time":1671625940000,"price":30,"user":{"uid":9276,"name":"CHARLY-チャリ"},"medal":{"level":29,"name":"帕清姬","boat":2}},{"content":"我现在是38.5度，本来打算降温，但是看到你在直播，我现在想升温了希望你和我贴贴","time":1671625971000,"price":30,"user":{"uid":483790777,"name":"梦幻白夜是也"},"medal":{"level":2,"name":"MUSU部","boat":0}},{"content":"3Dライブ頑張ってね！かのんちゃん天才ですから、きっとうまくできるよ!","time":1671626094000,"price":100,"user":{"uid":21954698,"name":"komichiaya"},"medal":{"level":26,"name":"帕清姬","boat":3}},{"content":"白菜，我今晚很忙可能照顾不到你。千万别往心里去，我永远爱你。","time":1671626250000,"price":30,"user":{"uid":108216062,"name":"喂女人干什么"},"medal":{"level":26,"name":"帕清姬","boat":3}},{"content":"统计截止到明天23:59哦，明天在舰队里就可以，话说抽奖的礼物是啥来着（","time":1671626613000,"price":30,"user":{"uid":246954,"name":"edeN滸"},"medal":{"level":29,"name":"帕清姬","boat":2}},{"content":"白菜隔壁正在聊你","time":1671626675000,"price":30,"user":{"uid":424424317,"name":"桜丶咲雪"},"medal":{"level":22,"name":"Luu民","boat":0}},{"content":"この配信のタグをつけたらpachi勝てますか？","time":1671626876000,"price":30,"user":{"uid":289629258,"name":"超絶核地雷"},"medal":{"level":25,"name":"光水晶","boat":3}},{"content":"戻ってくるよ必ず！２nd Attack！","time":1671626912000,"price":30,"user":{"uid":289629258,"name":"超絶核地雷"},"medal":{"level":25,"name":"光水晶","boat":3}},{"content":"あんただけは！落とす！3rd　ATTACK！","time":1671626938000,"price":30,"user":{"uid":289629258,"name":"超絶核地雷"},"medal":{"level":25,"name":"光水晶","boat":3}},{"content":"加油白菜！周末要研究生考试的我也很紧张！","time":1671626962000,"price":50,"user":{"uid":10049030,"name":"七情了了"},"medal":{"level":21,"name":"帕清姬","boat":3}},{"content":"白菜别紧张哦~深呼吸~放轻松~明天白菜一定没问题的~大家会为你加油的~mua","time":1671627071000,"price":30,"user":{"uid":7387975,"name":"l喵喵兔兔"},"medal":{"level":25,"name":"帕清姬","boat":3}},{"content":"緊張する時は観客を野菜だと思えばいいってよく言うよね、わたしはかぼちゃでいい","time":1671627701000,"price":30,"user":{"uid":9276,"name":"CHARLY-チャリ"},"medal":{"level":29,"name":"帕清姬","boat":2}},{"content":"在手上写个“人”字，一口气吃下去","time":1671627758000,"price":30,"user":{"uid":102771394,"name":"xxxprc"},"medal":{"level":22,"name":"帕清姬","boat":3}},{"content":"看白菜的时候一直都是dokidoki","time":1671627766000,"price":30,"user":{"uid":226227906,"name":"tetep_名無しさん"},"medal":{"level":26,"name":"小鹿包","boat":3}},{"content":"去看了白菜的动态，舰长抽奖的莉莉艾礼盒是之前话题度很高的那个吗","time":1671627914000,"price":30,"user":{"uid":1644948486,"name":"淳煜あめ_Official"},"medal":{"level":24,"name":"帕清姬","boat":3}},{"content":"そして可愛い女の子のカードが高い。これが人間の真理。","time":1671628086000,"price":30,"user":{"uid":487364787,"name":"Purin_琦玉老哥"},"medal":{"level":29,"name":"帕清姬","boat":3}},{"content":"如果抽中莉莉艾的卡牌，白菜可以签名再给我嘛","time":1671628302000,"price":30,"user":{"uid":32787603,"name":"衰神附体孙褐瞳"},"medal":{"level":27,"name":"帕清姬","boat":3}},{"content":"第一次sc就给白菜了 顺便麻烦念一下这个 握诗寻百才  白兰沾地衣  遥闻卧灰刹  齐返岸醉行","time":1671628363000,"price":50,"user":{"uid":37257454,"name":"幻影梅西"}},{"content":"PC看白菜，PAD看古守，手机看PARYI,还要吃烧烤，喝啤酒，有点累。。。。。","time":1671629199000,"price":30,"user":{"uid":206226312,"name":"切片观赏仙人"},"medal":{"level":23,"name":"打工鬼","boat":3}},{"content":"啤酒突然不好喝了。。。。","time":1671631036000,"price":30,"user":{"uid":206226312,"name":"切片观赏仙人"},"medal":{"level":23,"name":"打工鬼","boat":3}},{"content":"是谁教会他使用火龙。败我酒兴的？请麻溜的站出来","time":1671631344000,"price":30,"user":{"uid":206226312,"name":"切片观赏仙人"},"medal":{"level":23,"name":"打工鬼","boat":3}},{"content":"刚才打冰窟无尽丢了三个车，血压很高，结果这两局直接把我变成低血压了……","time":1671634226000,"price":30,"user":{"uid":453140891,"name":"B-18007"},"medal":{"level":24,"name":"帕清姬","boat":3}},{"content":"天才白菜","time":1671634476000,"price":30,"user":{"uid":37733470,"name":"拉面1314"},"medal":{"level":11,"name":"储备娘","boat":0}},{"content":"白菜这么聪明，打一拳应该不会变傻吧","time":1671634575000,"price":30,"user":{"uid":37733470,"name":"拉面1314"},"medal":{"level":12,"name":"帕清姬","boat":0}},{"content":"白菜，今天是22日，我过生日啦。因为生病我今天吃不到好吃的了，给我唱首甜甜的歌吧。同时祝晚上的LIVE顺利。mua抱抱","time":1671638736000,"price":100,"user":{"uid":861490,"name":"白菜的蓝好人"},"medal":{"level":25,"name":"帕清姬","boat":3}},{"content":"白菜早点休息  晚上加油  期待ing","time":1671639148000,"price":30,"user":{"uid":4644577,"name":"Pets韵"},"medal":{"level":21,"name":"帕清姬","boat":3}}]